goblinfish/aws/local/api_gateway/fastapi.py
goblinfish/aws/local/api_gateway/helpers.py
goblinfish_aws_local_lpi_apis-0.0.3.dist-info/licenses/LICENSE
goblinfish_aws_local_lpi_apis-0.0.3.dist-info/METADATA
goblinfish_aws_local_lpi_apis-0.0.3.dist-info/WHEEL
goblinfish_aws_local_lpi_apis-0.0.3.dist-info/top_level.txt
goblinfish_aws_local_lpi_apis-0.0.3.dist-info/RECORD
