Metadata-Version: 2.4
Name: goblinfish-aws-local-lpi-apis
Version: 0.0.3
Summary: Allows local application endpoints (FastAPI and eventually Flask) to call functions designed as AWS Lambda Function handlers.
Author-email: Brian Allbee <brian.allbee+goblinfish.lpi_apis@gmail.com>
Maintainer-email: Brian Allbee <brian.allbee+goblinfish.lpi_apis@gmail.com>
License: MIT License
Project-URL: Repository, https://bitbucket.org/stonefish-software-studio/goblinfish-aws-local-lpi_apis
Project-URL: Related Blog Posts, https://goblinfish-code.blogspot.com/search/label/local.lpi_apis
Keywords: aws,lambda,api gateway,fastapi,flask,local development
Classifier: Programming Language :: Python :: 3.13
Classifier: Programming Language :: Python :: 3.12
Classifier: Programming Language :: Python :: 3.11
Classifier: Programming Language :: Python :: 3
Classifier: Development Status :: 2 - Pre-Alpha
Classifier: Intended Audience :: Developers
Classifier: License :: OSI Approved :: MIT License
Classifier: Natural Language :: English
Classifier: Operating System :: OS Independent
Classifier: Framework :: FastAPI
Classifier: Topic :: Internet :: WWW/HTTP
Classifier: Topic :: Internet :: WWW/HTTP :: HTTP Servers
Classifier: Topic :: Internet :: WWW/HTTP :: WSGI :: Server
Requires-Python: >=3.11
License-File: LICENSE
Requires-Dist: fastapi<1
Requires-Dist: uvicorn<1
Requires-Dist: watchfiles<2
Requires-Dist: python-multipart<1
Requires-Dist: awslambdaric<4
Requires-Dist: fastapi<1
Dynamic: license-file
